{
    "hunter_walking": {
        "filename": "data/graphics/enemy_hunter_s.png",
        "frames" : 1,
        "frameDuration": [0.15],
        "playType" : "LOOP",
        "columns": 1,
        "rows" : 1
    },
    "paparazzi_walking": {
        "filename": "data/graphics/enemy_paparazzi_s.png",
        "frames" : 1,
        "frameDuration": [0.15],
        "playType" : "LOOP",
        "columns": 1,
        "rows" : 1
    },
    "unicorn_walking": {
        "filename": "data/graphics/unicorn_s.png",
        "frames" : 1,
        "frameDuration": [0.15],
        "playType" : "LOOP",
        "columns": 1,
        "rows" : 1
    },
    "unicorn_idle": {
        "filename": "data/graphics/unicorn_s.png",
        "frames" : 1,
        "frameDuration": [0.15],
        "playType" : "LOOP",
        "columns": 1,
        "rows" : 1
    },
    "unicorn_falling": {
        "filename": "data/graphics/unicorn_s.png",
        "frames" : 1,
        "frameDuration": [0.15],
        "playType" : "LOOP",
        "columns": 1,
        "rows" : 1
    },
    
    "walking": {
        "filename": "data/animations/walking.png",
        "frames" : 7,
        "frameDuration": [0.15, 0.15, 0.15, 0.15, 0.15, 0.15, 0.15],
        "playType" : "LOOP",
        "columns": 7,
        "rows" : 1
    },
    "ball": {
        "filename": "data/animations/ball.png",
        "frames" : 2,
        "frameDuration": [0.5, 0.5],
        "playType" : "LOOP",
        "columns": 2,
        "rows" : 1
    },
    "box": {
        "filename": "data/animations/box.png",
        "frames" : 2,
        "frameDuration": [0.5, 0.5],
        "playType" : "LOOP",
        "columns": 2,
        "rows" : 1
    }
}
